{
  "key": "sentry.op",
  "brief": "The operation of a span.",
  "type": "string",
  "apply_scrubbing": {
    "key": "never"
  },
  "is_in_otel": false,
  "example": "http.client",
  "visibility": "public",
  "search_aliases": [
    {
      "public_alias": "span.op",
      "internal_name": "sentry.op",
      "search_type": "string",
      "dataset_mappings": {
        "spans": "op",
        "eap": "attr_str[sentry.op]"
      }
    }
  ],
  "changelog": [
    {
      "version": "0.0.0"
    }
  ]
}
